LICENSE
MANIFEST.in
README.md
setup.py
AgileCLU/__init__.py
AgileCLU.egg-info/PKG-INFO
AgileCLU.egg-info/SOURCES.txt
AgileCLU.egg-info/dependency_links.txt
AgileCLU.egg-info/requires.txt
AgileCLU.egg-info/top_level.txt
bin/agilefetch
bin/agilefetch.py
bin/agilels
bin/agilels.py
bin/agilemkdir
bin/agilemkdir.py
bin/agilepost
bin/agilepost.py
bin/agileprofile
bin/agileprofile.py
bin/agilerm
bin/agilerm.py
bin/agilermdir
bin/agilermdir.py