Metadata-Version: 1.0
Name: AgileCLU
Version: 0.4.2
Summary: Agile Command Line Utilities
Home-page: http://pypi.python.org/pypi/AgileCLU
Author: Wylie Swanson
Author-email: wylie@pingzero.net
License: UNKNOWN
Download-URL: https://github.com/wylieswanson/AgileCLU/raw/master/dist/AgileCLU-0.4.2.tar.gz
Keywords: agile,storage,limelight,cloud,object
Platform: Any
Classifier: Development Status :: 4 - Beta
Classifier: License :: OSI Approved :: BSD License
Classifier: Programming Language :: Python
Classifier: Intended Audience :: End Users/Desktop
Classifier: Environment :: Console
Classifier: Topic :: Utilities
